{
  "scraped_data": {
    "The Price We Pay 2023": [
      "https://t.tarahipro.ir/1401/10/30/01/The.Price.We.Pay.2023.1080p.WEB-DL-ZF.mkv",
      " https://t.tarahipro.ir/1401/10/30/01/The.Price.We.Pay.2023.720p.WEB-DL-ZF.mkv",
      " https://t.tarahipro.ir/1401/10/30/01/The.Price.We.Pay.2023.480p.WEB-DL-ZF.mkv"
    ],
    "Dog Gone 2023": [
      "http://dl6.sermovie.xyz/Movie/2023/Dog.Gone.2023/Dog.Gone.2023.1080p.WEBRip.x264.AAC5.1-YTS.Sermovie.mp4",
      " http://dl6.sermovie.xyz/Movie/2023/Dog.Gone.2023/Dog.Gone.2023.720p.WEBRip.x264.AAC-YTS.Sermovie.mp4"
    ],
    "The Old Way 2023": [
      "http://dl6.sermovie.xyz/Movie/2023/The.Old.Way.2023/The.Old.Way.2023.1080p.WEBRip.x264.AAC5.1-YTS.Sermovie.mp4",
      " http://dl6.sermovie.xyz/Movie/2023/The.Old.Way.2023/The.Old.Way.2023.720p.WEBRip.x264.AAC-YTS.Sermovie.mp4",
      " http://dl6.sermovie.xyz/Movie/2023/The.Old.Way.2023/The.Old.Way.2023.720p.10bit.WEBRip.6CH.x265.HEVC-PSA.Sermovie.mkv",
      " http://dl6.sermovie.xyz/Movie/2023/The.Old.Way.2023/The.Old.Way.2023.480p.WEBRip.x264.RMT.Sermovie.mkv"
    ],
    "The Point Men 2023": [
      "http://dl6.sermovie.xyz/Movie/2023/The.Point.Men.2023/The.Point.Men.2023.WEB-DL.1080p.x265.SoftSub.Sermovie.mkv",
      " http://dl6.sermovie.xyz/Movie/2023/The.Point.Men.2023/The.Point.Men.2023.WEB-DL.720p.x265.SoftSub.Sermovie.mkv",
      " http://dl6.sermovie.xyz/Movie/2023/The.Point.Men.2023/The.Point.Men.2023.WEB-DL.480p.SoftSub.Sermovie.mkv"
    ],
    "Gangs of Lagos 2023": [
      "https://www.sabishare.com/file/yAlRrvvCo08-gangs-of-lagos-2023-netnaija-com-mkv"
    ],
    "Shazam Fury of the Gods 2023": [
      "https://dl11.uploding.fun/Movies4/2023/Shazam_Fury_of_the_Gods_2023/Shazam_Fury_of_the_Gods_2023_10bit_DV_HDR_2160p_x265_WEB-DL_Dolby_Atmos_CMRG.mkv",
      " https://dl11.uploding.fun/Movies4/2023/Shazam_Fury_of_the_Gods_2023/Shazam_Fury_of_the_Gods_2023_1080p_WEB-DL_YIFY.mkv",
      " https://dl11.uploding.fun/Movies4/2023/Shazam_Fury_of_the_Gods_2023/Shazam_Fury_of_the_Gods_2023_720p_WEB-DL_YIFY.mkv",
      " https://dl11.uploding.fun/Movies4/2023/Shazam_Fury_of_the_Gods_2023/Shazam_Fury_of_the_Gods_2023_10bit_720p_x265_WEB-DL_6CH_PSA.mkv",
      " http://dl6.sermovie.xyz/Movie/2023/Shazam.Fury.of.the.Gods.2023/Shazam.Fury.of.the.Gods.2023.480p.WEB-DL.x264-Pahe.SoftSub.Sermovie.mkv"
    ],
    "Inside 2023": [
      "http://dl6.sermovie.xyz/Movie/2023/Inside.2023/Inside.2023.1080p.WEBRip.x264.AAC5.1-YTS.SoftSub.Sermovie.mp4",
      " http://dl6.sermovie.xyz/Movie/2023/Inside.2023/Inside.2023.720p.WEBRip.x264.AAC-YTS.SoftSub.Sermovie.mp4",
      " http://dl6.sermovie.xyz/Movie/2023/Inside.2023/Inside.2023.720p.10bit.WEBRip.6CH.x265.HEVC-PSA.SoftSub.Sermovie.mkv"
    ],
    "Transfusion 2023": [
      "http://dl6.sermovie.xyz/Movie/2023/Transfusion.2023/Transfusion.2023.1080p.WEBRip.x264.AAC-YTS.SoftSub.Sermovie.mp4",
      " http://dl6.sermovie.xyz/Movie/2023/Transfusion.2023/Transfusion.2023.720p.WEBRip.x264.AAC-YTS.SoftSub.Sermovie.mp4"
    ],
    "Operation Fortune Ruse de Guerre 2023": [
      "http://dl6.sermovie.xyz/Movie/2023/Operation.Fortune.Ruse.De.Guerre.2022/Operation.Fortune.Ruse.De.Guerre.2023.1080p.BluRay.x264.YTS.SoftSub.Sermovie.mp4",
      " http://dl6.sermovie.xyz/Movie/2023/Operation.Fortune.Ruse.De.Guerre.2022/Operation.Fortune.Ruse.De.Guerre.2023.1080p.10bit.BluRay.6CH.x265.HEVC-PSA.SoftSub.Sermovie.mkv",
      " http://dl6.sermovie.xyz/Movie/2023/Operation.Fortune.Ruse.De.Guerre.2022/Operation.Fortune.Ruse.De.Guerre.2023.720p.BluRay.x264.YTS.SoftSub.Sermovie.mp4",
      " http://dl6.sermovie.xyz/Movie/2023/Operation.Fortune.Ruse.De.Guerre.2022/Operation.Fortune.Ruse.De.Guerre.2023.720p.10bit.BluRay.6CH.x265.HEVC-PSA.SoftSub.Sermovie.mkv"
    ],
    "Luther The Fallen Sun 2023": [
      "http://dl6.sermovie.xyz/Movie/2023/Luther.The.Fallen.Sun.2023/Luther.The.Fallen.Sun.2023.1080p.WEBRip.x264-RARBG.SoftSub.Sermovie.mp4",
      " http://dl6.sermovie.xyz/Movie/2023/Luther.The.Fallen.Sun.2023/Luther.The.Fallen.Sun.2023.720p.NF.WEBRip.900MB.x264-GalaxyRG.SoftSub.Sermovie.mkv",
      " http://dl6.sermovie.xyz/Movie/2023/Luther.The.Fallen.Sun.2023/Luther.The.Fallen.Sun.2023.720p.10bit.WEBRip.6CH.x265.HEVC-PSA.SoftSub.Sermovie.mkv",
      " http://dl6.sermovie.xyz/Movie/2023/Luther.The.Fallen.Sun.2023/Luther.The.Fallen.Sun.2023.480p.WEBRip.x264.RMT.SoftSub.Sermovie.mkv"
    ],
    "Chupa 2023": [
      "http://dl6.sermovie.xyz/Movie/2023/Chupa.2023/Chupa.2023.1080p.WEBRip.x264.AAC5.1-YTS.Sermovie.mp4",
      " http://dl6.sermovie.xyz/Movie/2023/Chupa.2023/Chupa.2023.720p.WEBRip.x264.AAC5.1-YTS.Sermovie.mp4"
    ],
    "Champions 2023": [
      "http://dl6.sermovie.xyz/Movie/2023/Champions.2023/Champions.2023.1080p.WEBRip.x264.AAC5.1-YTS.Sermovie.mp4",
      " http://dl6.sermovie.xyz/Movie/2023/Champions.2023/Champions.2023.720p.WEBRip.x264.AAC-YTS.Sermovie.mp4",
      " http://dl6.sermovie.xyz/Movie/2023/Champions.2023/Champions.2023.720p.10bit.WEBRip.6CH.x265.HEVC-PSA.Sermovie.mkv",
      " http://dl6.sermovie.xyz/Movie/2023/Champions.2023/Champions.2023.480p.WEBRip.x264.RMT.Sermovie.mkv"
    ],
    "Mummies 2023": [
      "https://dl11.uploding.fun/Movies4/2023/Mummies_2023/Mummies_2023_1080p_WEB-DL_YIFY.mkv",
      " https://dl11.uploding.fun/Movies4/2023/Mummies_2023/Mummies_2023_720p_WEB-DL_YIFY.mkv"
    ],
    "The Ritual Killer 2023": [
      "http://dl6.sermovie.xyz/Movie/2023/The.Ritual.Killer.2023/The.Ritual.Killer.2023.1080p.AMZN.WEBRip.1400MB.DD5.1.x264-GalaxyRG.Sermovie.mkv",
      " http://dl6.sermovie.xyz/Movie/2023/The.Ritual.Killer.2023/The.Ritual.Killer.2023.720p.AMZN.WEBRip.800MB.x264-GalaxyRG.Sermovie.mkv",
      " http://dl6.sermovie.xyz/Movie/2023/The.Ritual.Killer.2023/The.Ritual.Killer.2023.720p.10bit.WEBRip.6CH.x265.HEVC-PSA.Sermovie.mkv"
    ],
    "Detective Knight Independence 2023": [
      "http://dl6.sermovie.xyz/Movie/2023/Detective.Knight.Independence.2023/Detective.Knight.Independence.2023.1080p.WEBRip.x264.AAC5.1-YTS.Sermovie.mp4",
      " http://dl6.sermovie.xyz/Movie/2023/Detective.Knight.Independence.2023/Detective.Knight.Independence.2023.720p.WEBRip.x264.AAC-YTS.Sermovie.mp4"
    ],
    "80 For Brady 2023": [
      "http://dl6.sermovie.xyz/Movie/2023/80.for.Brady.2023/80.For.Brady.2023.1080p.WEBRip.x264.AAC5.1-YTS.Sermovie.mp4",
      " http://dl6.sermovie.xyz/Movie/2023/80.for.Brady.2023/80.For.Brady.2023.720p.WEBRip.x264.AAC-YTS.Sermovie.mp4"
    ],
    "Missing 2023": [
      "http://dl6.sermovie.xyz/Movie/2023/Missing.2023/Missing.2023.1080p.WEB-DL.x264.6CH.Pahe.SoftSub.Sermovie.mkv",
      " http://dl6.sermovie.xyz/Movie/2023/Missing.2023/Missing.2023.720p.WEB-DL.x264.Pahe.SoftSub.Sermovie.mkv",
      " http://dl6.sermovie.xyz/Movie/2023/Missing.2023/Missing.2023.720p.10bit.WEB-DL.6CH.x265.HEVC.PSA.SoftSub.Sermovie.mkv"
    ],
    "Johnny and Clyde 2023": [
      "http://dl6.sermovie.xyz/Movie/2023/Johnny.and.Clyde.2023/Johnny.and.Clyde.2023.1080p.WEBRip.x264.AAC5.1-YTS.Sermovie.mp4",
      " http://dl6.sermovie.xyz/Movie/2023/Johnny.and.Clyde.2023/Johnny.and.Clyde.2023.720p.WEBRip.x264.AAC-YTS.Sermovie.mp4",
      " http://dl6.sermovie.xyz/Movie/2023/Johnny.and.Clyde.2023/Johnny.and.Clyde.2023.720p.10bit.WEBRip.6CH.x265.HEVC-PSA.Sermovie.mkv"
    ],
    "The Locksmith 2023": [
      "http://dl6.sermovie.xyz/Movie/2023/The.Locksmith.2023/The.Locksmith.2023.1080p.WEB-DL.x264.YIFY.SoftSub.Sermovie.mkv",
      " http://dl6.sermovie.xyz/Movie/2023/The.Locksmith.2023/The.Locksmith.2023.720p.WEB-DL.x264.YIFY.SoftSub.Sermovie.mkv"
    ],
    "Die Hart The Movie 2023": [
      "https://dl.bamabin42.workers.dev/0:/Die.Hart.The.Movie.2023.1080p.WEB-DL.x264.AAC5.1-YIFY.Bamabin.mp4",
      " https://dl.bamabin42.workers.dev/0:/Die.Hart.The.Movie.2023.720p.WEB-DL.x264.AAC-YIFY.Bamabin.mp4",
      " https://dl.bamabin42.workers.dev/0:/Die.Hart.The.Movie.2023.480p.WEB-DL.x264-RMTeam.Bamabin.mkv"
    ],
    "65 2023": [
      "http://dl6.sermovie.xyz/Movie/2023/65.2023/65.2023.1080p.Full.HD.MA.WEB.DL.DDP5.1.FLUX.SoftSub.Sermovie.mkv",
      " http://dl6.sermovie.xyz/Movie/2023/65.2023/65.2023.1080p.WEBRip.x264.AAC5.1-YTS.SoftSub.Sermovie.mp4",
      " http://dl6.sermovie.xyz/Movie/2023/65.2023/65.2023.720p.WEBRip.x264.AAC-YTS.SoftSub.Sermovie.mp4",
      " http://dl6.sermovie.xyz/Movie/2023/65.2023/65.2023.720p.10bit.WEBRip.6CH.x265.HEVC-PSA.SoftSub.Sermovie.mkv",
      " http://dl6.sermovie.xyz/Movie/2023/65.2023/65.2023.480p.WEBRip.x264.RMT.SoftSub.Sermovie.mkv"
    ]
  },
  "imglnk": "https://miro.medium.com/max/2160/0*WFJUV6w1MGI32y1P",
  "movie_type": "movie",
  "query": "2023",
  "page_title": "",
  "is_local": false
}